aiotdk/__init__.py
aiotdk/gts/__init__.py
aiotdk-0.0.1.dist-info/LICENSE
aiotdk-0.0.1.dist-info/METADATA
aiotdk-0.0.1.dist-info/WHEEL
aiotdk-0.0.1.dist-info/top_level.txt
aiotdk-0.0.1.dist-info/RECORD
